[{"authors": [{"affiliation": [], "given": "Bj\u00f6rn", "family": "Nykvist"}, {"affiliation": [], "given": "M\u00e5ns", "family": "Nilsson"}], "doi": "10.1038/nclimate2564", "title": "Rapidly falling costs of battery packs for electric\u00a0vehicles", "journal": "Nature Climate Change", "year": "2015-3", "cite": "250", "pub": "Springer Nature", "issn": "1758-678X"}, {"authors": [{"affiliation": [], "given": "S.", "family": "Asseng"}, {"affiliation": [], "given": "F.", "family": "Ewert"}, {"affiliation": [], "given": "P.", "family": "Martre"}, {"affiliation": [], "given": "R. P.", "family": "R\u00f6tter"}, {"affiliation": [], "given": "D. B.", "family": "Lobell"}, {"affiliation": [], "given": "D.", "family": "Cammarano"}, {"affiliation": [], "given": "B. A.", "family": "Kimball"}, {"affiliation": [], "given": "M. J.", "family": "Ottman"}, {"affiliation": [], "given": "G. W.", "family": "Wall"}, {"affiliation": [], "given": "J. W.", "family": "White"}, {"affiliation": [], "given": "M. P.", "family": "Reynolds"}, {"affiliation": [], "given": "P. D.", "family": "Alderman"}, {"affiliation": [], "given": "P. V. V.", "family": "Prasad"}, {"affiliation": [], "given": "P. K.", "family": "Aggarwal"}, {"affiliation": [], "given": "J.", "family": "Anothai"}, {"affiliation": [], "given": "B.", "family": "Basso"}, {"affiliation": [], "given": "C.", "family": "Biernath"}, {"affiliation": [], "given": "A. J.", "family": "Challinor"}, {"affiliation": [], "given": "G.", "family": "De Sanctis"}, {"affiliation": [], "given": "J.", "family": "Doltra"}, {"affiliation": [], "given": "E.", "family": "Fereres"}, {"affiliation": [], "given": "M.", "family": "Garcia-Vila"}, {"affiliation": [], "given": "S.", "family": "Gayler"}, {"affiliation": [], "given": "G.", "family": "Hoogenboom"}, {"affiliation": [], "given": "L. A.", "family": "Hunt"}, {"affiliation": [], "given": "R. C.", "family": "Izaurralde"}, {"affiliation": [], "given": "M.", "family": "Jabloun"}, {"affiliation": [], "given": "C. D.", "family": "Jones"}, {"affiliation": [], "given": "K. C.", "family": "Kersebaum"}, {"affiliation": [], "given": "A-K.", "family": "Koehler"}, {"affiliation": [], "given": "C.", "family": "M\u00fcller"}, {"affiliation": [], "given": "S.", "family": "Naresh Kumar"}, {"affiliation": [], "given": "C.", "family": "Nendel"}, {"affiliation": [], "given": "G.", "family": "O\u2019Leary"}, {"affiliation": [], "given": "J. E.", "family": "Olesen"}, {"affiliation": [], "given": "T.", "family": "Palosuo"}, {"affiliation": [], "given": "E.", "family": "Priesack"}, {"affiliation": [], "given": "E.", "family": "Eyshi Rezaei"}, {"affiliation": [], "given": "A. C.", "family": "Ruane"}, {"affiliation": [], "given": "M. A.", "family": "Semenov"}, {"affiliation": [], "given": "I.", "family": "Shcherbak"}, {"affiliation": [], "given": "C.", "family": "St\u00f6ckle"}, {"affiliation": [], "given": "P.", "family": "Stratonovitch"}, {"affiliation": [], "given": "T.", "family": "Streck"}, {"affiliation": [], "given": "I.", "family": "Supit"}, {"affiliation": [], "given": "F.", "family": "Tao"}, {"affiliation": [], "given": "P. J.", "family": "Thorburn"}, {"affiliation": [], "given": "K.", "family": "Waha"}, {"affiliation": [], "given": "E.", "family": "Wang"}, {"affiliation": [], "given": "D.", "family": "Wallach"}, {"affiliation": [], "given": "J.", "family": "Wolf"}, {"affiliation": [], "given": "Z.", "family": "Zhao"}, {"affiliation": [], "given": "Y.", "family": "Zhu"}], "doi": "10.1038/nclimate2470", "title": "Rising temperatures reduce global wheat\u00a0production", "journal": "Nature Climate Change", "year": "2014-12", "cite": "160", "pub": "Springer Nature", "issn": "1758-678X"}, {"authors": [{"affiliation": [], "given": "N.", "family": "Pepin"}, {"affiliation": [], "given": "R. S.", "family": "Bradley"}, {"affiliation": [], "given": "H. F.", "family": "Diaz"}, {"affiliation": [], "given": "M.", "family": "Baraer"}, {"affiliation": [], "given": "E. B.", "family": "Caceres"}, {"affiliation": [], "given": "N.", "family": "Forsythe"}, {"affiliation": [], "given": "H.", "family": "Fowler"}, {"affiliation": [], "given": "G.", "family": "Greenwood"}, {"affiliation": [], "given": "M. Z.", "family": "Hashmi"}, {"affiliation": [], "given": "X. D.", "family": "Liu"}, {"affiliation": [], "given": "J. R.", "family": "Miller"}, {"affiliation": [], "given": "L.", "family": "Ning"}, {"affiliation": [], "given": "A.", "family": "Ohmura"}, {"affiliation": [], "given": "E.", "family": "Palazzi"}, {"affiliation": [], "given": "I.", "family": "Rangwala"}, {"affiliation": [], "given": "W.", "family": "Sch\u00f6ner"}, {"affiliation": [], "given": "I.", "family": "Severskiy"}, {"affiliation": [], "given": "M.", "family": "Shahgedanova"}, {"affiliation": [], "given": "M. B.", "family": "Wang"}, {"affiliation": [], "given": "S. N.", "family": "Williamson"}, {"affiliation": [], "given": "D. Q.", "family": "Yang"}], "doi": "10.1038/nclimate2563", "title": "Elevation-dependent warming in mountain regions of the world", "journal": "Nature Climate Change", "year": "2015-4", "cite": "159", "pub": "Springer Nature", "issn": "1758-678X"}, {"authors": [{"affiliation": [], "given": "Sabine", "family": "Fuss"}, {"affiliation": [], "given": "Josep G.", "family": "Canadell"}, {"affiliation": [], "given": "Glen P.", "family": "Peters"}, {"affiliation": [], "given": "Massimo", "family": "Tavoni"}, {"affiliation": [], "given": "Robbie M.", "family": "Andrew"}, {"affiliation": [], "given": "Philippe", "family": "Ciais"}, {"affiliation": [], "given": "Robert B.", "family": "Jackson"}, {"affiliation": [], "given": "Chris D.", "family": "Jones"}, {"affiliation": [], "given": "Florian", "family": "Kraxner"}, {"affiliation": [], "given": "Nebosja", "family": "Nakicenovic"}, {"affiliation": [], "given": "Corinne", "family": "Le Qu\u00e9r\u00e9"}, {"affiliation": [], "given": "Michael R.", "family": "Raupach"}, {"affiliation": [], "given": "Ayyoob", "family": "Sharifi"}, {"affiliation": [], "given": "Pete", "family": "Smith"}, {"affiliation": [], "given": "Yoshiki", "family": "Yamagata"}], "doi": "10.1038/nclimate2392", "title": "Betting on negative emissions", "journal": "Nature Climate Change", "year": "2014-9", "cite": "140", "pub": "Springer Nature", "issn": "1758-678X"}, {"authors": [{"affiliation": [], "given": "J. S.", "family": "Famiglietti"}], "doi": "10.1038/nclimate2425", "title": "The global groundwater crisis", "journal": "Nature Climate Change", "year": "2014-10", "cite": "129", "pub": "Springer Nature", "issn": "1758-678X"}, {"authors": [{"affiliation": [], "given": "Stefan", "family": "Rahmstorf"}, {"affiliation": [], "given": "Jason E.", "family": "Box"}, {"affiliation": [], "given": "Georg", "family": "Feulner"}, {"affiliation": [], "given": "Michael E.", "family": "Mann"}, {"affiliation": [], "given": "Alexander", "family": "Robinson"}, {"affiliation": [], "given": "Scott", "family": "Rutherford"}, {"affiliation": [], "given": "Erik J.", "family": "Schaffernicht"}], "doi": "10.1038/nclimate2554", "title": "Exceptional twentieth-century slowdown in Atlantic Ocean overturning circulation", "journal": "Nature Climate Change", "year": "2015-3", "cite": "127", "pub": "Springer Nature", "issn": "1758-678X"}, {"authors": [{"affiliation": [], "given": "Michela", "family": "Pacifici"}, {"affiliation": [], "given": "Wendy B.", "family": "Foden"}, {"affiliation": [], "given": "Piero", "family": "Visconti"}, {"affiliation": [], "given": "James E. M.", "family": "Watson"}, {"affiliation": [], "given": "Stuart H.M.", "family": "Butchart"}, {"affiliation": [], "given": "Kit M.", "family": "Kovacs"}, {"affiliation": [], "given": "Brett R.", "family": "Scheffers"}, {"affiliation": [], "given": "David G.", "family": "Hole"}, {"affiliation": [], "given": "Tara G.", "family": "Martin"}, {"affiliation": [], "given": "H. Resit", "family": "Ak\u00e7akaya"}, {"affiliation": [], "given": "Richard T.", "family": "Corlett"}, {"affiliation": [], "given": "Brian", "family": "Huntley"}, {"affiliation": [], "given": "David", "family": "Bickford"}, {"affiliation": [], "given": "Jamie A.", "family": "Carr"}, {"affiliation": [], "given": "Ary A.", "family": "Hoffmann"}, {"affiliation": [], "given": "Guy F.", "family": "Midgley"}, {"affiliation": [], "given": "Paul", "family": "Pearce-Kelly"}, {"affiliation": [], "given": "Richard G.", "family": "Pearson"}, {"affiliation": [], "given": "Stephen E.", "family": "Williams"}, {"affiliation": [], "given": "Stephen G.", "family": "Willis"}, {"affiliation": [], "given": "Bruce", "family": "Young"}, {"affiliation": [], "given": "Carlo", "family": "Rondinini"}], "doi": "10.1038/nclimate2448", "title": "Assessing species vulnerability to climate change", "journal": "Nature Climate Change", "year": "2015-2", "cite": "117", "pub": "Springer Nature", "issn": "1758-678X"}, {"authors": [{"affiliation": [], "given": "E. M.", "family": "Fischer"}, {"affiliation": [], "given": "R.", "family": "Knutti"}], "doi": "10.1038/nclimate2617", "title": "Anthropogenic contribution to global occurrence\u00a0of heavy-precipitation and\u00a0high-temperature extremes", "journal": "Nature Climate Change", "year": "2015-4", "cite": "115", "pub": "Springer Nature", "issn": "1758-678X"}, {"authors": [{"affiliation": [{"name": "Senior Research Associate, Guttmacher Institute, 125 Maiden Lane, New York, NY 10038."}], "given": "Gilda", "family": "Sedgh"}, {"affiliation": [{"name": "Vice President for Research, Guttmacher Institute, 125 Maiden Lane, New York, NY 10038."}], "given": "Susheela", "family": "Singh"}, {"affiliation": [{"name": "Research Associate, Guttmacher Institute, 125 Maiden Lane, New York, NY 10038."}], "given": "Rubina", "family": "Hussain"}], "doi": "10.1111/j.1728-4465.2014.00393.x", "title": "Intended and Unintended Pregnancies Worldwide in 2012 and Recent Trends", "journal": "Studies in Family Planning", "year": "2014-9", "cite": "114", "pub": "Wiley-Blackwell", "issn": "0039-3665"}, {"authors": [{"affiliation": [], "given": "Wenju", "family": "Cai"}, {"affiliation": [], "given": "Guojian", "family": "Wang"}, {"affiliation": [], "given": "Agus", "family": "Santoso"}, {"affiliation": [], "given": "Michael J.", "family": "McPhaden"}, {"affiliation": [], "given": "Lixin", "family": "Wu"}, {"affiliation": [], "given": "Fei-Fei", "family": "Jin"}, {"affiliation": [], "given": "Axel", "family": "Timmermann"}, {"affiliation": [], "given": "Mat", "family": "Collins"}, {"affiliation": [], "given": "Gabriel", "family": "Vecchi"}, {"affiliation": [], "given": "Matthieu", "family": "Lengaigne"}, {"affiliation": [], "given": "Matthew H.", "family": "England"}, {"affiliation": [], "given": "Dietmar", "family": "Dommenget"}, {"affiliation": [], "given": "Ken", "family": "Takahashi"}, {"affiliation": [], "given": "Eric", "family": "Guilyardi"}], "doi": "10.1038/nclimate2492", "title": "Increased frequency of extreme La\u00a0Ni\u00f1a events under greenhouse warming", "journal": "Nature Climate Change", "year": "2015-1", "cite": "104", "pub": "Springer Nature", "issn": "1758-678X"}, {"authors": [{"affiliation": [], "given": "Dean", "family": "Roemmich"}, {"affiliation": [], "given": "John", "family": "Church"}, {"affiliation": [], "given": "John", "family": "Gilson"}, {"affiliation": [], "given": "Didier", "family": "Monselesan"}, {"affiliation": [], "given": "Philip", "family": "Sutton"}, {"affiliation": [], "given": "Susan", "family": "Wijffels"}], "doi": "10.1038/nclimate2513", "title": "Unabated planetary warming and its ocean structure since 2006", "journal": "Nature Climate Change", "year": "2015-2", "cite": "94", "pub": "Springer Nature", "issn": "1758-678X"}, {"authors": [{"affiliation": [], "given": "Pete", "family": "Smith"}, {"affiliation": [], "given": "Steven J.", "family": "Davis"}, {"affiliation": [], "given": "Felix", "family": "Creutzig"}, {"affiliation": [], "given": "Sabine", "family": "Fuss"}, {"affiliation": [], "given": "Jan", "family": "Minx"}, {"affiliation": [], "given": "Benoit", "family": "Gabrielle"}, {"ORCID": "http://orcid.org/0000-0001-8814-804X", "authenticated-orcid": false, "given": "Etsushi", "family": "Kato", "affiliation": []}, {"affiliation": [], "given": "Robert B.", "family": "Jackson"}, {"affiliation": [], "given": "Annette", "family": "Cowie"}, {"affiliation": [], "given": "Elmar", "family": "Kriegler"}, {"affiliation": [], "given": "Detlef P.", "family": "van Vuuren"}, {"ORCID": "http://orcid.org/0000-0003-2056-9061", "authenticated-orcid": false, "given": "Joeri", "family": "Rogelj", "affiliation": []}, {"affiliation": [], "given": "Philippe", "family": "Ciais"}, {"affiliation": [], "given": "Jennifer", "family": "Milne"}, {"affiliation": [], "given": "Josep G.", "family": "Canadell"}, {"affiliation": [], "given": "David", "family": "McCollum"}, {"ORCID": "http://orcid.org/0000-0001-7889-8568", "authenticated-orcid": false, "given": "Glen", "family": "Peters", "affiliation": []}, {"ORCID": "http://orcid.org/0000-0001-8590-6431", "authenticated-orcid": false, "given": "Robbie", "family": "Andrew", "affiliation": []}, {"affiliation": [], "given": "Volker", "family": "Krey"}, {"ORCID": "http://orcid.org/0000-0001-7150-8731", "authenticated-orcid": false, "given": "Gyami", "family": "Shrestha", "affiliation": []}, {"ORCID": "http://orcid.org/0000-0003-3309-4739", "authenticated-orcid": false, "given": "Pierre", "family": "Friedlingstein", "affiliation": []}, {"affiliation": [], "given": "Thomas", "family": "Gasser"}, {"affiliation": [], "given": "Arnulf", "family": "Gr\u00fcbler"}, {"affiliation": [], "given": "Wolfgang K.", "family": "Heidug"}, {"affiliation": [], "given": "Matthias", "family": "Jonas"}, {"affiliation": [], "given": "Chris D.", "family": "Jones"}, {"affiliation": [], "given": "Florian", "family": "Kraxner"}, {"affiliation": [], "given": "Emma", "family": "Littleton"}, {"affiliation": [], "given": "Jason", "family": "Lowe"}, {"affiliation": [], "given": "Jos\u00e9 Roberto", "family": "Moreira"}, {"affiliation": [], "given": "Nebojsa", "family": "Nakicenovic"}, {"affiliation": [], "given": "Michael", "family": "Obersteiner"}, {"affiliation": [], "given": "Anand", "family": "Patwardhan"}, {"affiliation": [], "given": "Mathis", "family": "Rogner"}, {"affiliation": [], "given": "Ed", "family": "Rubin"}, {"ORCID": "http://orcid.org/0000-0002-8983-8613", "authenticated-orcid": false, "given": "Ayyoob", "family": "Sharifi", "affiliation": []}, {"affiliation": [], "given": "Asbj\u00f8rn", "family": "Torvanger"}, {"affiliation": [], "given": "Yoshiki", "family": "Yamagata"}, {"affiliation": [], "given": "Jae", "family": "Edmonds"}, {"affiliation": [], "given": "Cho", "family": "Yongsung"}], "doi": "10.1038/nclimate2870", "title": "Biophysical and economic limits to negative CO2 emissions", "journal": "Nature Climate Change", "year": "2015-12", "cite": "90", "pub": "Springer Nature", "issn": "1758-678X"}, {"authors": [{"affiliation": [], "given": "Kevin E.", "family": "Trenberth"}, {"affiliation": [], "given": "John T.", "family": "Fasullo"}, {"affiliation": [], "given": "Theodore G.", "family": "Shepherd"}], "doi": "10.1038/nclimate2657", "title": "Attribution of climate extreme events", "journal": "Nature Climate Change", "year": "2015-6", "cite": "89", "pub": "Springer Nature", "issn": "1758-678X"}, {"authors": [{"affiliation": [], "given": "Michael R.", "family": "Raupach"}, {"affiliation": [], "given": "Steven J.", "family": "Davis"}, {"ORCID": "http://orcid.org/0000-0001-7889-8568", "authenticated-orcid": false, "given": "Glen P.", "family": "Peters", "affiliation": []}, {"affiliation": [], "given": "Robbie M.", "family": "Andrew"}, {"affiliation": [], "given": "Josep G.", "family": "Canadell"}, {"affiliation": [], "given": "Philippe", "family": "Ciais"}, {"affiliation": [], "given": "Pierre", "family": "Friedlingstein"}, {"affiliation": [], "given": "Frank", "family": "Jotzo"}, {"affiliation": [], "given": "Detlef P.", "family": "van Vuuren"}, {"affiliation": [], "given": "Corinne", "family": "Le Qu\u00e9r\u00e9"}], "doi": "10.1038/nclimate2384", "title": "Sharing a quota on cumulative carbon emissions", "journal": "Nature Climate Change", "year": "2014-9", "cite": "83", "pub": "Springer Nature", "issn": "1758-678X"}, {"authors": [{"affiliation": [], "given": "Gerald A.", "family": "Meehl"}, {"affiliation": [], "given": "Haiyan", "family": "Teng"}, {"affiliation": [], "given": "Julie M.", "family": "Arblaster"}], "doi": "10.1038/nclimate2357", "title": "Climate model simulations of the observed early-2000s hiatus of global warming", "journal": "Nature Climate Change", "year": "2014-9", "cite": "81", "pub": "Springer Nature", "issn": "1758-678X"}, {"authors": [{"affiliation": [], "given": "Nathan G.", "family": "McDowell"}, {"affiliation": [], "given": "Craig D.", "family": "Allen"}], "doi": "10.1038/nclimate2641", "title": "Darcy's law predicts widespread forest mortality under climate warming", "journal": "Nature Climate Change", "year": "2015-5", "cite": "79", "pub": "Springer Nature", "issn": "1758-678X"}, {"authors": [{"affiliation": [], "given": "Aiguo", "family": "Dai"}, {"affiliation": [], "given": "John C.", "family": "Fyfe"}, {"affiliation": [], "given": "Shang-Ping", "family": "Xie"}, {"affiliation": [], "given": "Xingang", "family": "Dai"}], "doi": "10.1038/nclimate2605", "title": "Decadal modulation of global surface temperature by internal climate variability", "journal": "Nature Climate Change", "year": "2015-4", "cite": "77", "pub": "Springer Nature", "issn": "1758-678X"}, {"authors": [{"affiliation": [], "given": "Joeri", "family": "Rogelj"}, {"affiliation": [], "given": "Gunnar", "family": "Luderer"}, {"ORCID": "http://orcid.org/0000-0002-9403-6711", "authenticated-orcid": false, "given": "Robert C.", "family": "Pietzcker", "affiliation": []}, {"affiliation": [], "given": "Elmar", "family": "Kriegler"}, {"affiliation": [], "given": "Michiel", "family": "Schaeffer"}, {"affiliation": [], "given": "Volker", "family": "Krey"}, {"affiliation": [], "given": "Keywan", "family": "Riahi"}], "doi": "10.1038/nclimate2572", "title": "Energy system transformations for limiting end-of-century warming to below 1.5 \u00b0C", "journal": "Nature Climate Change", "year": "2015-5", "cite": "75", "pub": "Springer Nature", "issn": "1758-678X"}, {"authors": [{"affiliation": [], "given": "Deborah", "family": "Lawrence"}, {"affiliation": [], "given": "Karen", "family": "Vandecar"}], "doi": "10.1038/nclimate2430", "title": "Effects of tropical deforestation on climate and agriculture", "journal": "Nature Climate Change", "year": "2014-12", "cite": "75", "pub": "Springer Nature", "issn": "1758-678X"}, {"authors": [{"affiliation": [], "given": "Frank", "family": "Seebacher"}, {"affiliation": [], "given": "Craig R.", "family": "White"}, {"affiliation": [], "given": "Craig E.", "family": "Franklin"}], "doi": "10.1038/nclimate2457", "title": "Physiological plasticity increases resilience of ectothermic animals to climate change", "journal": "Nature Climate Change", "year": "2014-12", "cite": "73", "pub": "Springer Nature", "issn": "1758-678X"}]